django_rahavard_robots/__init__.py
django_rahavard_robots/apps.py
django_rahavard_robots/urls.py
django_rahavard_robots/views.py
django_rahavard_robots/migrations/__init__.py
django_rahavard_robots-0.0.2.dist-info/LICENSE
django_rahavard_robots-0.0.2.dist-info/METADATA
django_rahavard_robots-0.0.2.dist-info/WHEEL
django_rahavard_robots-0.0.2.dist-info/top_level.txt
django_rahavard_robots-0.0.2.dist-info/RECORD
